pd2img/__init__.py
pd2img-0.0.3.dist-info/METADATA
pd2img-0.0.3.dist-info/WHEEL
pd2img-0.0.3.dist-info/top_level.txt
pd2img-0.0.3.dist-info/RECORD
