Metadata-Version: 2.1
Name: pd2img
Version: 0.0.3
Summary: Convert RGB/RGBA image files to pandas dataframes, and vice versa
Home-page: UNKNOWN
Author: hansalemao
Author-email: <aulasparticularesdealemaosp@gmail.com>
License: UNKNOWN
Keywords: pandas,opencv,images,dataframe,pd,np
Platform: UNKNOWN
Classifier: Development Status :: 1 - Planning
Classifier: Intended Audience :: Developers
Classifier: Programming Language :: Python :: 3
Classifier: Operating System :: Unix
Classifier: Operating System :: MacOS :: MacOS X
Classifier: Operating System :: Microsoft :: Windows
Requires-Dist: opencv-python
Requires-Dist: pandas
Requires-Dist: numpy
Requires-Dist: Pillow
